ann_backpropagation_algorithm/__init__.py
ann_backpropagation_algorithm/main.py
ann_backpropagation_algorithm-0.3.3.dist-info/METADATA
ann_backpropagation_algorithm-0.3.3.dist-info/WHEEL
ann_backpropagation_algorithm-0.3.3.dist-info/entry_points.txt
ann_backpropagation_algorithm-0.3.3.dist-info/top_level.txt
ann_backpropagation_algorithm-0.3.3.dist-info/RECORD
