Metadata-Version: 2.1
Name: ann_backpropagation_algorithm
Version: 0.3.3
Summary: A package for backpropagation algorithm implementation.
Author: Arasu
Author-email: arasu6262@gmail.com
